apm/__init__.py
apm/const.py
apm/exceptions.py
apm/instrumentation.py
ms_common_py-0.2.0.dist-info/METADATA
ms_common_py-0.2.0.dist-info/WHEEL
ms_common_py-0.2.0.dist-info/top_level.txt
ms_common_py-0.2.0.dist-info/RECORD
