Metadata-Version: 2.4
Name: ms-common-py
Version: 0.2.0
Summary: A comprehensive APM and instrumentation library for Python microservices
Home-page: https://bitbucket.org/finaccelteam/ms-common-py
Author: FinAccel Team
Author-email: shivam.pradhan@finaccel.co
Requires-Python: >=3.9
Requires-Dist: ddtrace>=2.2.0
Dynamic: author-email
Dynamic: home-page
